uapi/__init__.py
uapi/client.py
uapi/config.py
uapi/core.py
uapi/version.py
uapi_sdk-0.1.3.dist-info/METADATA
uapi_sdk-0.1.3.dist-info/WHEEL
uapi_sdk-0.1.3.dist-info/top_level.txt
uapi_sdk-0.1.3.dist-info/RECORD
