Metadata-Version: 2.4
Name: uapi-sdk
Version: 0.1.3
Summary: A simple SDK for discovering and accessing API endpoints
Requires-Python: >=3.7
Requires-Dist: requests>=2.31.0
Requires-Dist: typing-extensions>=4.5.0
Dynamic: requires-dist
Dynamic: requires-python
Dynamic: summary
